{
	"#pgIslemlerim": {
		"backgroundColor": {
			"startColor": "rgba(56,191,242,1)",
			"endColor": "rgba(41,152,227,1)",
			"direction": "VERTICAL"
		},
		"flexProps": {
			"alignItems": "STRETCH"
		},
		"paddingTop": 8,
		"&-title": {
			"font": {
				"size": 28,
				"family": "SFProText",
				"style": "Semibold",
				"bold": true,
				"italic": false
			},
			"height": 41,
			"textColor": "rgba(255,255,255,1)",
			"marginTop": 8,
			"marginLeft": 15
		},
		"&-mainItems": {
			"height": 130,
			"flexProps": {
				"flexDirection": "ROW",
				"alignItems": "CENTER"
			}
		},
		"&-subMenu": {
			"flexProps": {
				"flexGrow": 1
			},
			"height": null,
			"backgroundColor": "rgba(255,255,255,1)",
			"borderRadius": 20,
			"marginBottom": -20,
			"marginTop": 10,
			"paddingLeft": 15,
			"paddingRight": 15,
			"paddingTop": 22
		},
		"paddingBottom": 0
	}
}